AUTHORS.rst
CONTRIBUTING.rst
HISTORY.rst
LICENSE
MANIFEST.in
README.rst
setup.py
git2json/__init__.py
git2json/parser.py
git2json.egg-info/PKG-INFO
git2json.egg-info/SOURCES.txt
git2json.egg-info/dependency_links.txt
git2json.egg-info/entry_points.txt
git2json.egg-info/not-zip-safe
git2json.egg-info/top_level.txt