Metadata-Version: 1.1
Name: git2json
Version: 0.2.1
Summary: Convert git logs to JSON for easier analysis.
Home-page: https://github.com/tarmstrong/git2json
Author: Tavish Armstrong
Author-email: tavisharmstrong@gmail.com
License: BSD
Keywords: git2json
Platform: UNKNOWN
Classifier: Development Status :: 2 - Pre-Alpha
Classifier: Intended Audience :: Developers
Classifier: License :: OSI Approved :: BSD License
Classifier: Natural Language :: English
Classifier: Programming Language :: Python :: 2
Classifier: Programming Language :: Python :: 2.6
Classifier: Programming Language :: Python :: 2.7
Classifier: Programming Language :: Python :: 3
Classifier: Programming Language :: Python :: 3.3
